zstdarchiver/__init__.py
zstdarchiver/zstdarchiver.py
zstdarchiver/plugins/__init__.py
zstdarchiver/plugins/crypt/__init__.py
zstdarchiver/plugins/crypt/default.py
zstdarchiver/plugins/meta/__init__.py
zstdarchiver/plugins/meta/mozilla.py
zstdarchiver-0.2.0.dist-info/LICENSE.txt
zstdarchiver-0.2.0.dist-info/METADATA
zstdarchiver-0.2.0.dist-info/WHEEL
zstdarchiver-0.2.0.dist-info/top_level.txt
zstdarchiver-0.2.0.dist-info/RECORD
